mathsimple/__init__.py
mathsimple/operations.py
mathsimple-0.1.0.dist-info/licenses/LICENSE.txt
mathsimple-0.1.0.dist-info/METADATA
mathsimple-0.1.0.dist-info/WHEEL
mathsimple-0.1.0.dist-info/top_level.txt
mathsimple-0.1.0.dist-info/RECORD
