Metadata-Version: 2.4
Name: mathsimple
Version: 0.1.0
Summary: A simple math package for basic arithmetic
Author: rama
Author-email: rama5864@gmail.com
Requires-Python: >=3.6
License-File: LICENSE.txt
Dynamic: author
Dynamic: author-email
Dynamic: description
Dynamic: description-content-type
Dynamic: license-file
Dynamic: requires-python
Dynamic: summary
